aimmo/__init__.py
aimmo/admin.py
aimmo/app_settings.py
aimmo/exceptions.py
aimmo/game_renderer.py
aimmo/models.py
aimmo/permissions.py
aimmo/setup.py
aimmo/urls.py
aimmo/views.py
aimmo/worksheets.py
aimmo/avatar_examples/__init__.py
aimmo/avatar_examples/attacking_avatar.py
aimmo/avatar_examples/health_seeker_avatar.py
aimmo/avatar_examples/random_avatar.py
aimmo/avatar_examples/simple_avatar.py
aimmo/avatar_examples/winner_avatar.py
aimmo/game_manager/__init__.py
aimmo/game_manager/constants.py
aimmo/game_manager/game_ingress_manager.py
aimmo/game_manager/game_manager.py
aimmo/game_manager/game_secret_manager.py
aimmo/game_manager/game_server_manager.py
aimmo/game_manager/game_service_manager.py
aimmo/management/__init__.py
aimmo/management/commands/__init__.py
aimmo/management/commands/delete_generated_players.py
aimmo/management/commands/generate_players.py
aimmo/management/commands/start_game_servers_for_running_games.py
aimmo/middleware/__init__.py
aimmo/middleware/game_limit_exceeded.py
aimmo/migrations/0001_initial.py
aimmo/migrations/0002_auto_20160601_1914.py
aimmo/migrations/0003_auto_20160802_1418.py
aimmo/migrations/0004_auto_20160808_1511.py
aimmo/migrations/0005_auto_20160808_1545.py
aimmo/migrations/0006_game_static_data.py
aimmo/migrations/0007_auto_20180515_1300.py
aimmo/migrations/0008_default_public_field.py
aimmo/migrations/0009_add_game_status.py
aimmo/migrations/0010_alter_game_token.py
aimmo/migrations/0011_reset_game_tokens.py
aimmo/migrations/0012_auto_20200302_1310.py
aimmo/migrations/0013_alter_game_can_play.py
aimmo/migrations/0014_add_worksheet_model.py
aimmo/migrations/0015_game_worksheet.py
aimmo/migrations/0016_game_class.py
aimmo/migrations/0017_add_worksheet_1_and_2.py
aimmo/migrations/0018_set_worksheet_2_as_default_for_games.py
aimmo/migrations/0019_game_has_worksheet_and_class.py
aimmo/migrations/0020_add_info_to_worksheet.py
aimmo/migrations/0021_add_pdf_names_to_worksheet.py
aimmo/migrations/0022_allow_games_to_have_no_name.py
aimmo-2.11.3.dist-info/LICENSE.md
aimmo-2.11.3.dist-info/METADATA
aimmo-2.11.3.dist-info/WHEEL
aimmo-2.11.3.dist-info/top_level.txt
aimmo-2.11.3.dist-info/RECORD
