Metadata-Version: 2.1
Name: aimmo
Version: 2.11.3
License-File: LICENSE.md
Requires-Dist: cfl-common
Requires-Dist: django ==3.2.25
Requires-Dist: django-csp ==3.7
Requires-Dist: django-js-reverse ==0.9.1
Requires-Dist: djangorestframework ==3.13.1
Requires-Dist: eventlet ==0.31.0
Requires-Dist: hypothesis ==5.41.3
Requires-Dist: kubernetes ==26.1.0
Requires-Dist: requests ==2.32.2
